LICENSE
MANIFEST.in
README.rst
setup.py
admin_bootstrapped_plus/__init__.py
admin_bootstrapped_plus/tests.py
admin_bootstrapped_plus/static/admin_bootstrapped_plus/css/admin_bootstrapped_plus.css
admin_bootstrapped_plus/templates/admin/base.html
admin_bootstrapped_plus/templates/admin/index.html
django_admin_bootstrapped_plus.egg-info/PKG-INFO
django_admin_bootstrapped_plus.egg-info/SOURCES.txt
django_admin_bootstrapped_plus.egg-info/dependency_links.txt
django_admin_bootstrapped_plus.egg-info/requires.txt
django_admin_bootstrapped_plus.egg-info/top_level.txt