Metadata-Version: 1.1
Name: django-admin-bootstrapped-plus
Version: 0.1.0
Summary: Django Admin Bootstrapped Plus provides a vertical sidebar to the standard Django admin pages.
Home-page: https://github.com/Wtower/django-admin-bootstrapped-plus/
Author: George Karakostas
Author-email: info@9-dev.com
License: BSD-3 License
Keywords: admin theme
Platform: UNKNOWN
Classifier: Environment :: Web Environment
Classifier: Framework :: Django
Classifier: Intended Audience :: Developers
Classifier: License :: OSI Approved :: BSD License
Classifier: Operating System :: OS Independent
Classifier: Programming Language :: Python
Classifier: Programming Language :: Python :: 3
Classifier: Programming Language :: Python :: 3.4
Classifier: Programming Language :: Python :: 3.5
Classifier: Topic :: Internet :: WWW/HTTP
Classifier: Topic :: Internet :: WWW/HTTP :: Dynamic Content
